winipedia_django/__init__.py
winipedia_django/dev/__init__.py
winipedia_django/dev/artifacts/__init__.py
winipedia_django/dev/artifacts/builder/__init__.py
winipedia_django/dev/artifacts/builder/builder.py
winipedia_django/dev/artifacts/builds/__init__.py
winipedia_django/dev/artifacts/builds/builder.py
winipedia_django/dev/cli/__init__.py
winipedia_django/dev/cli/subcommands.py
winipedia_django/dev/configs/__init__.py
winipedia_django/dev/configs/configs.py
winipedia_django/py.typed
winipedia_django/utils/__init__.py
winipedia_django/utils/commands/__init__.py
winipedia_django/utils/commands/base/__init__.py
winipedia_django/utils/commands/base/base.py
winipedia_django/utils/commands/import_data.py
winipedia_django/utils/db/__init__.py
winipedia_django/utils/db/bulk.py
winipedia_django/utils/db/fields.py
winipedia_django/utils/db/models.py
winipedia_django/utils/db/sql.py
winipedia_django-0.2.42.dist-info/METADATA
winipedia_django-0.2.42.dist-info/WHEEL
winipedia_django-0.2.42.dist-info/entry_points.txt
winipedia_django-0.2.42.dist-info/licenses/LICENSE
winipedia_django-0.2.42.dist-info/RECORD
