Metadata-Version: 2.4
Name: winipedia-django
Version: 0.2.42
Summary: A utils package for django
License-Expression: MIT
License-File: LICENSE
Author: Winipedia
Author-email: win.steveker@gmx.de
Requires-Python: >=3.12
Classifier: Programming Language :: Python :: 3
Classifier: Programming Language :: Python :: 3.12
Classifier: Programming Language :: Python :: 3.13
Classifier: Programming Language :: Python :: 3.14
Requires-Dist: django
Requires-Dist: winipedia-utils
